atlas_hfdatasets/__init__.py
atlas_hfdatasets/atlas_hfdatasets.py
atlas_hfdatasets/src/__init__.py
atlas_hfdatasets/src/check.py
atlas_hfdatasets/src/core_functions.py
atlas_hfdatasets/src/list.py
atlas_hfdatasets/src/rename.py
atlas_hfdatasets/src/upload.py
atlas_hfdatasets-1.3.9.dist-info/LICENSE
atlas_hfdatasets-1.3.9.dist-info/METADATA
atlas_hfdatasets-1.3.9.dist-info/WHEEL
atlas_hfdatasets-1.3.9.dist-info/entry_points.txt
atlas_hfdatasets-1.3.9.dist-info/top_level.txt
atlas_hfdatasets-1.3.9.dist-info/RECORD
