Metadata-Version: 2.1
Name: atlas_hfdatasets
Version: 1.3.9
Summary: Manage your datasets on the Hugging Face Hub
Home-page: https://github.com/yourusername/atlas_hfdatasets
Author: Haopeng Yu
Author-email: atlasbioin4@gmail.com
Classifier: Programming Language :: Python :: 3
Classifier: License :: OSI Approved :: MIT License
Classifier: Operating System :: OS Independent
Requires-Python: >=3.7
License-File: LICENSE
Requires-Dist: huggingface-hub
Requires-Dist: datasets
